README.md
setup.py
cep_range/__init__.py
cep_range/cep_range.py
cep_range.egg-info/PKG-INFO
cep_range.egg-info/SOURCES.txt
cep_range.egg-info/dependency_links.txt
cep_range.egg-info/requires.txt
cep_range.egg-info/top_level.txt