Metadata-Version: 2.1
Name: cep-range
Version: 0.0.1
Summary: UNKNOWN
Home-page: UNKNOWN
Author: Gabriel Gontijo
Author-email: gontijogabr@gmail.com
License: MIT License
Keywords: cep coordenadas geograficas enderecos postalcode address
Platform: UNKNOWN
